{
  "all_checks_pass": true,
  "arithmetic": "exact integer/GF(2) except explicitly reported floating residuals",
  "certificate_schema": "1.0.0",
  "checks": {
    "branch_weights_normalized": true,
    "code_parameters": true,
    "decoder_radius_one_exhaustive": true,
    "double_errors_rejected": true,
    "empirical_calibration_contract": true,
    "empirical_likelihood_contract": true,
    "garden_algebra_exact": true,
    "hypercube_edges_and_shells_exact": true,
    "hypercube_spectrum_exact": true,
    "markov_uniform_stationary": true,
    "nine_dimensional_code_not_self_dual": true,
    "parity_pair_flip_spectrum_exact": true,
    "physics_background_lumped": true,
    "physics_background_moments_exact": true,
    "physics_bridge_observables_normalized": true,
    "physics_generator_valid": true,
    "physics_kernel_stochastic": true,
    "physics_pair_flip_closed": true,
    "physics_perturbation_modes_bounded": true,
    "prediction_lock_contract": true,
    "projection_idempotent": true,
    "punctured_code_self_dual": true,
    "quotient_isomorphism": true,
    "standard_baseline_contract": true
  },
  "project_version": "1.1.0",
  "sections": {
    "adinkra": {
      "boson_map": {
        "0": 0,
        "10": 7,
        "12": 5,
        "15": 4,
        "3": 1,
        "5": 3,
        "6": 2,
        "9": 6
      },
      "color_permutation_one_based": [
        1,
        2,
        3,
        5,
        4,
        8,
        6,
        7
      ],
      "even_vertex_count": 8,
      "fermion_map": {
        "1": 4,
        "11": 3,
        "13": 1,
        "14": 0,
        "2": 5,
        "4": 7,
        "7": 6,
        "8": 2
      },
      "garden_algebra_holds": true,
      "kronecker_words": [
        "III",
        "IIJ",
        "IJX",
        "XJZ",
        "ZJZ",
        "JZX",
        "JIZ",
        "JXX"
      ],
      "matrix_count": 8,
      "matrix_edge_count": 64,
      "matrix_shape": [
        8,
        8
      ],
      "maximum_integer_residual": 0,
      "odd_vertex_count": 8,
      "quotient_edge_count": 64,
      "quotient_vertex_count": 16,
      "signed_permutation": true,
      "valid": true
    },
    "branching": {
      "all_leaf_states_integrity_valid": true,
      "coordinate_8_preserved": true,
      "depth": 4,
      "expected_leaf_count": 81,
      "geometry_rule": "FF[+F]F[-F]",
      "geometry_segments_iteration_2": 25,
      "leaf_count": 81,
      "leaf_weight_sum": 1.0,
      "node_count": 121,
      "unique_messages": 16
    },
    "code": {
      "coordinate_8_invariant": true,
      "coordinate_9_active": true,
      "coordinate_9_parity": true,
      "doubly_even": true,
      "dual_size": 32,
      "length": 9,
      "minimum_distance": 4,
      "punctured_length": 8,
      "punctured_minimum_distance": 4,
      "punctured_rank": 4,
      "punctured_self_dual": true,
      "rank": 4,
      "self_dual_in_f2_9": false,
      "self_orthogonal": true,
      "size": 16,
      "weight_distribution": {
        "0": 1,
        "4": 14,
        "8": 1
      }
    },
    "decoder": {
      "affine_exact_checks": 4096,
      "affine_single_error_checks": 36864,
      "double_error_rejection_checks": 576,
      "full_state_status_counts": {
        "corrected": 144,
        "exact": 16,
        "uncorrectable": 352
      },
      "nearest_distance_and_tie_counts": {
        "distance_0_nearest_1": 16,
        "distance_1_nearest_1": 144,
        "distance_2_nearest_1": 128,
        "distance_2_nearest_4": 112,
        "distance_3_nearest_4": 112
      },
      "silent_correction_beyond_radius_one": false,
      "single_error_checks": 144
    },
    "empirical_bridge": {
      "best_likelihood_model": "close",
      "calibrated_unit": "m",
      "calibrated_value": 14.5,
      "calibration_source": "mean_hamming_weight",
      "calibration_target": "example_length",
      "comparison_count": 2,
      "example_chi_square": 1.25,
      "example_log_likelihood": -1.7697298858494,
      "interpretation": "Calibration and likelihood contracts only; no external data fit is claimed."
    },
    "hypercube": {
      "adjacency_spectrum": [
        {
          "eigenvalue": 9,
          "multiplicity": 1
        },
        {
          "eigenvalue": 7,
          "multiplicity": 9
        },
        {
          "eigenvalue": 5,
          "multiplicity": 36
        },
        {
          "eigenvalue": 3,
          "multiplicity": 84
        },
        {
          "eigenvalue": 1,
          "multiplicity": 126
        },
        {
          "eigenvalue": -1,
          "multiplicity": 126
        },
        {
          "eigenvalue": -3,
          "multiplicity": 84
        },
        {
          "eigenvalue": -5,
          "multiplicity": 36
        },
        {
          "eigenvalue": -7,
          "multiplicity": 9
        },
        {
          "eigenvalue": -9,
          "multiplicity": 1
        }
      ],
      "adjacency_square_trace": 4608,
      "adjacency_trace": 0,
      "all_integrity_states_valid": true,
      "distance_shell_counts": [
        1,
        9,
        36,
        84,
        126,
        126,
        84,
        36,
        9,
        1
      ],
      "each_state_neighbor_count": 9,
      "edge_count": 2304,
      "even_parity_shell_counts": [
        1,
        36,
        126,
        84,
        9
      ],
      "full_orbit_count": 32,
      "integrity_orbit_count": 16,
      "integrity_state_count": 256,
      "laplacian_spectral_gap": 2,
      "laplacian_spectrum": [
        {
          "eigenvalue": 0,
          "multiplicity": 1
        },
        {
          "eigenvalue": 2,
          "multiplicity": 9
        },
        {
          "eigenvalue": 4,
          "multiplicity": 36
        },
        {
          "eigenvalue": 6,
          "multiplicity": 84
        },
        {
          "eigenvalue": 8,
          "multiplicity": 126
        },
        {
          "eigenvalue": 10,
          "multiplicity": 126
        },
        {
          "eigenvalue": 12,
          "multiplicity": 84
        },
        {
          "eigenvalue": 14,
          "multiplicity": 36
        },
        {
          "eigenvalue": 16,
          "multiplicity": 9
        },
        {
          "eigenvalue": 18,
          "multiplicity": 1
        }
      ],
      "orbit_size": 16,
      "pair_flip_adjacency_spectrum": [
        {
          "eigenvalue": 36,
          "multiplicity": 1
        },
        {
          "eigenvalue": 20,
          "multiplicity": 9
        },
        {
          "eigenvalue": 8,
          "multiplicity": 36
        },
        {
          "eigenvalue": 0,
          "multiplicity": 84
        },
        {
          "eigenvalue": -4,
          "multiplicity": 126
        }
      ],
      "pair_flip_adjacency_square_trace": 9216,
      "pair_flip_adjacency_trace": 0,
      "pair_flip_graph_degree": 36,
      "pair_flip_graph_edge_count": 4608,
      "pair_flip_laplacian_spectral_gap": 16,
      "pair_flip_laplacian_spectrum": [
        {
          "eigenvalue": 0,
          "multiplicity": 1
        },
        {
          "eigenvalue": 16,
          "multiplicity": 9
        },
        {
          "eigenvalue": 28,
          "multiplicity": 36
        },
        {
          "eigenvalue": 36,
          "multiplicity": 84
        },
        {
          "eigenvalue": 40,
          "multiplicity": 126
        }
      ],
      "plane_counts": [
        1,
        9,
        36,
        84,
        126,
        126,
        84,
        36,
        9,
        1
      ],
      "reference_row_count": 512,
      "state_count": 512
    },
    "markov_chain": {
      "column_sum_max_abs_error": 0.0,
      "interpretation": "The binomial Hamming marginal follows from uniform occupancy; it is not ASH-specific evidence.",
      "minimum_self_loop_probability": 0.8,
      "noise_probability_checked": 0.2,
      "positive_hypercube_edges": 4608,
      "row_sum_max_abs_error": 0.0,
      "uniform_hamming_marginal": [
        0.001953125,
        0.017578125,
        0.0703125,
        0.1640625,
        0.24609375,
        0.24609375,
        0.1640625,
        0.0703125,
        0.017578125,
        0.001953125
      ],
      "uniform_stationary_max_abs_error": 0.0
    },
    "physics": {
      "all_states_parity_valid": true,
      "background_row_sum_max_abs_error": 0.0,
      "evolved_weight_distribution_mean": 1.7902716049382714,
      "evolved_weight_distribution_sum": 1.0,
      "generator_row_sum_max_abs_error": 0.0,
      "generator_symmetry_max_abs_error": 0.0,
      "interpretation": "Finite-observer stochastic physics layer; not an observational cosmology claim.",
      "kernel_row_sum_max_abs_error": 0.0,
      "kernel_symmetry_max_abs_error": 0.0,
      "lazy_pair_flip_mode_factors": [
        1.0,
        0.8444444444444444,
        0.7277777777777777,
        0.65,
        0.6111111111111112,
        0.6111111111111112,
        0.65,
        0.7277777777777777,
        0.8444444444444444,
        1.0
      ],
      "mode_factors_bounded": true,
      "pair_flip_probability_checked": 0.35,
      "pair_flip_rate_checked": 1.25,
      "state_count": 256,
      "uniform_background_distribution": [
        0.00390625,
        0.140625,
        0.4921875,
        0.328125,
        0.03515625
      ],
      "uniform_background_mean_hamming_weight": 4.5,
      "uniform_background_order_parameter": 0.0,
      "uniform_background_stationary_max_abs_error": 0.0,
      "uniform_background_variance_hamming_weight": 2.25,
      "uniform_entropy_bits": 8.0,
      "uniform_mean_hamming_weight": 4.5,
      "uniform_order_parameter": 0.0,
      "uniform_parity_valid_probability": 1.0,
      "uniform_stationary_max_abs_error": 0.0,
      "weight_level_degeneracies": [
        1,
        36,
        126,
        84,
        9
      ]
    },
    "prediction_ledger": {
      "empty_entry_status": "no_locked_predictions",
      "entry_hash_length": 64,
      "entry_hash_validates": true,
      "interpretation": "Prediction-lock mechanics are implemented; no repository prediction is locked by this example.",
      "locked_entry_status": "has_locked_predictions"
    },
    "projection": {
      "codeword_count": 16,
      "constant_preserved": true,
      "idempotence_max_abs_error": 0.0,
      "output_is_code_invariant": true,
      "state_count": 512
    },
    "standard_baseline": {
      "best_baseline": "standard",
      "best_baseline_chi_square": 0.0,
      "dark_energy_density": 0.7,
      "distance_curve": [
        0.0,
        0.44098433481065213,
        0.7714271046433859
      ],
      "distance_curve_monotonic": true,
      "hubble_at_one": 1.7606816861659007,
      "hubble_at_zero": 1.0,
      "interpretation": "Standard-baseline comparison mechanics only; not an ASH-derived cosmology limit.",
      "matter_density": 0.3,
      "total_density": 1.0
    }
  },
  "source_sha256": {
    ".github/discussion_agents.json": "c365f2ff57d5ac8300c9259758d31ed7472991c4a4377abcfab505d8d0eabeed",
    ".github/discussion_moderation_policy.json": "9c36fe2175f0ab44bbc772a5c51183005db3fdc09d3ee15fab09c0fef8d784f0",
    ".github/discussion_topic_generator.json": "d3577968de38698de9b412eb16535a097adee1497dd53cb4cc2de41339e67743",
    ".github/pull_request_template.md": "36b782cc83237ce54dbeb1a0b276a2d8f90980b24ee015f9c47b8a334de46b84",
    ".github/wiki-sync.json": "4e6574ae35406099bc590ace2f5b7e78183efe2ea9844937a89367a4591d33cf",
    ".github/workflows/ai-contributor-check.yml": "63b5126948288a8e84a7867bdf0af7e73d56fadb742f5f1ef4d7efea690fad24",
    ".github/workflows/changelog-validation.yml": "3f561661e0336919569b479d8a0f9d5f5410e6ededb315f6fbfd05bbc1b108f8",
    ".github/workflows/ci.yml": "efba106e9439e9c3860d8e803f90aaa7ef5ce1cd8c5b347fc911ff389226e7c6",
    ".github/workflows/contributor-identity-check.yml": "0448e6b2f3a4ab0b5ebd2dcf718809c96787217929f72e5a86184a0681f9d495",
    ".github/workflows/discussion-agents.yml": "c6533fda5958d4a5d5f66c1412226242b89a11ed5d3eb5e7aa74028f5e315061",
    ".github/workflows/discussion-moderation.yml": "2b39b1fda3ea6af95e764a74a059f73853b863bf2a12d933feae202bd13d4f38",
    ".github/workflows/discussion-topic-seeder.yml": "01793bf70249b85b7031a77bd6bf71e6cb4f9f9fa16bf360fd528f1906a50354",
    ".github/workflows/version-assignment.yml": "16da058a4aae7b307f10b42edb9bbb01915c330e163e4601e389c61fc066a69d",
    ".github/workflows/version-tracking.yml": "c0b48320c709597eac441fa7851ebfda645cf57530ca0bc1ac47a279bffdbcc7",
    ".github/workflows/wiki-sync.yml": "253b57f4a311ac1b2c4ab1f73f8fc901a8fb187069dc124e7ee294f5a10e33a2",
    ".gitignore": "dd75deedc0d7c3affc277d674eac46c702e1a58ef33879fee054f6335a446a1e",
    "CITATION.cff": "ce7ea23d646e1ed15f317e141b03773a64d71146fdf1bed904c1dea626c6058e",
    "CODE_OF_CONDUCT.md": "d62908e6788db8f909131bd0ef64a38a943758d68653b5e29f942b448ede2b60",
    "CONTRIBUTING.md": "df82eb27c381df7d89e8e7bd87ceef8458268e7c3b54cebc320d158a082a449d",
    "LICENSE": "213910e1405c0866a1200da12f1dcd5a4f41ed3d4a82c9c78acf85e6f5f304a6",
    "README.md": "857ceed14fb8e2dbe0a861b8f3b1b44d17a57fa6684c35b3b71b412bd0f180dc",
    "VERSION": "1575e1af4a95f12f70b4ee6a6adce8160953d93ea17dc2611b90883ccc3ad3b8",
    "axioms-of-existence.json": "f1a71833bb53b31e120d0591bd717999aeb23d729f58a29b8c9104a915bf25ef",
    "changelog/CHANGELOG.md": "bbfcd0a0160d6f856682c44f465d4bad8917745f7ee7e84e2c38d5345944be3f",
    "config/ash_mapping_v1.json": "aef24e8eba2441025e1e440e2791215d32d163e0b7b91d25bb7e9b7018260c79",
    "config/ash_physics_sector_mixing_v1.json": "01b94f02303e514aca5ae38af2269cfd12020a3fa43df3c0951ffa1aebb0ebd1",
    "data/ash-cosmology/branch-centered-roadmap/v0.2/MANIFEST.json": "ab87059196c387e2afa45b75bb661f72b50e5927d0231338c71074f6088eb384",
    "data/ash-cosmology/branch-centered-roadmap/v0.2/README.md": "b13137670e6e1b2c900fa10d6310ca1a95089d63056d0a527dcd49e85dddd156",
    "data/ash-cosmology/branch-centered-roadmap/v0.2/machine-readable/ash_cosmology_branch_centered_roadmap.json": "e0bb1d363821a26f572b4c6dcd3c1916922e486e7de42ec460489abb582e340b",
    "data/ash-cosmology/branch-centered-roadmap/v0.2/machine-readable/ash_cosmology_branch_centered_roadmap.yaml": "ec256006ca758abf9359c0845992f48ee816c0ea2a86aeee1d09cdbdf99d74e3",
    "data/ash-cosmology/branch-centered-roadmap/v0.2/machine-readable/ash_cosmology_roadmap.schema.json": "56d98511594dd136957623c7fd997a14289ad3f417efa36c278849c2ea679d7a",
    "data/ash-cosmology/branch-centered-roadmap/v0.2/machine-readable/branch_correction_lock.json": "e10e36dc43d7d933cf0abc562600fd94b891e327028c02ee24b04477d541551d",
    "data/ash-cosmology/branch-centered-roadmap/v0.2/machine-readable/deliverables_manifest.json": "cfa2a4fe57c1f184de1aded8b972a1108037e397dc38317839f19bff84913720",
    "data/ash-cosmology/branch-centered-roadmap/v0.2/machine-readable/dependency_graph.json": "63b3d542884052215c86b3b140dbda44368a1781bdfacaf27a0060bd3a85ad59",
    "data/ash-cosmology/branch-centered-roadmap/v0.2/machine-readable/empirical_experiment_catalog.json": "921cb0fb441421dedcebdc4b887e5dd4d6871431bfe0bf14cc6915b73dcad415",
    "data/ash-cosmology/branch-centered-roadmap/v0.2/machine-readable/evidence_ladder.json": "24bc67fa99d10123bf9947c11e4f65e8b359a90e587bba429c4a521fdad24ff3",
    "data/ash-cosmology/branch-centered-roadmap/v0.2/machine-readable/falsification_rules.json": "5fedf766d5a45961ba594b7185d9c063a790e7b1e1034135db278c68b34f9324",
    "data/ash-cosmology/branch-centered-roadmap/v0.2/machine-readable/glossary.json": "d081de062ce7004a67bb7384f39b887a84a406e3b3ca20926e1a4238fd714e3f",
    "data/ash-cosmology/branch-centered-roadmap/v0.2/machine-readable/mathematical_phase_catalog.json": "0b3e375281b9350cca90b5be59cf7f1a7ee0bbea7f5a8e6ac6dfae8d1f1afd51",
    "data/ash-cosmology/branch-centered-roadmap/v0.2/machine-readable/prediction_ledger_template.json": "9369b02c2f71a2f1c7b370ef71926d6d64b4ce35b36a5ccf5385e724464cc18b",
    "data/ash-cosmology/branch-centered-roadmap/v0.2/machine-readable/prediction_ledger_template.yaml": "b2f7ccec62eb2c13c9cacd34c2589f2b30e34b295fed074dc4ce5c912d385ea4",
    "data/ash-cosmology/branch-centered-roadmap/v0.2/machine-readable/theorem_catalog.json": "66081aadb86d1bee371d897b32f97b243da81cb08d1c7711eaf1818b7a5da2ef",
    "data/ash-physics-sector-mixing/README.md": "79e47ec0d2b1ab1bad16ff9296a17389c7216940e3536f4fa784d4bb25953134",
    "data/ash-physics-sector-mixing/upstream-payload-manifest.json": "858724465ab5145feb71c603019376a103c4df83dbfb51a7fba1500e081a039a",
    "data/branch-topology.json": "e114168b20ce2842126b949399b07750160fb0acbdf3971a028f5fcc15d3748c",
    "data/simulation-metadata.json": "666915a7c6d93b37e26eb9d1eca44b6fcba68f8d412871c8f40476727cc7b43a",
    "docs/ASH-research-paper.md": "bcfed7ba4ced8c1fe9ba5c85e12fb1b96d960062c24f49296e557bacac3ed43f",
    "docs/ash-cosmology/branch-centered-roadmap/v0.2/PACKAGE_README.md": "e53c444f0c39749db54cf12a22c1820a5205bd33abfa1cf4ba3101adcb922956",
    "docs/ash-cosmology/branch-centered-roadmap/v0.2/README.md": "40e7453e073c34552fb04b4151bdc26f2042228f9dc0f94c02bee9c7468a0f07",
    "docs/ash-cosmology/branch-centered-roadmap/v0.2/human-readable/00_LOCKED_POSITION.md": "9e963ba03b8ac1524aa9802b394e22c9d54d8d571c4a9faabbc2ac0daf042134",
    "docs/ash-cosmology/branch-centered-roadmap/v0.2/human-readable/01_CANONICAL_MODEL.md": "995b81afb673a43a7453d61653fd130b96789df3a11464ae10e838626297f3bf",
    "docs/ash-cosmology/branch-centered-roadmap/v0.2/human-readable/02_BRANCH_MANY_WORLDS_MODEL.md": "22110d25acfc6452452430d2c76c569d9098a9a8aa7ec766e489fc3d3dd75e8b",
    "docs/ash-cosmology/branch-centered-roadmap/v0.2/human-readable/03_MATHEMATICAL_PROOF_ROADMAP.md": "daa16f06283758bcb87239825f3217a2564e95c4f09b7797802bd03ac609db1f",
    "docs/ash-cosmology/branch-centered-roadmap/v0.2/human-readable/04_EMPIRICAL_VALIDATION_ROADMAP.md": "2e70fb0dc7dcb3b801452d53a71258b858d37da19ac8bd5988508a12521a9ab4",
    "docs/ash-cosmology/branch-centered-roadmap/v0.2/human-readable/05_FALSIFICATION_CRITERIA.md": "8c9256b07b32215e695dfcb63e62eaacd9c186fb2955db27e99411659cc1f2eb",
    "docs/ash-cosmology/branch-centered-roadmap/v0.2/human-readable/06_RESEARCH_DELIVERABLES.md": "f48e4ee11004951383169118a80fc4c5e837e469ca83c8d6169e2aa38aa82ce7",
    "docs/ash-cosmology/branch-centered-roadmap/v0.2/human-readable/07_PREDICTION_LEDGER_GUIDE.md": "fc78f152896117317649b67dde27c907c08e19bf718d53ffac86331ac814feaa",
    "docs/ash-cosmology/branch-centered-roadmap/v0.2/human-readable/08_GLOSSARY.md": "c765c5d0f9104dd1ed3b7f042a3160b3ffb59ac6184b9c875ece90992dd94265",
    "docs/ash-cosmology/branch-centered-roadmap/v0.2/human-readable/09_SOURCE_EVIDENCE_NOTES.md": "2ba2fcb6911c17b0cc6718e1a5dec4829c13d5c1e377364a62a5764849a367cb",
    "docs/ash-cosmology/branch-centered-roadmap/v0.2/human-readable/10_FULL_BRANCH_CENTERED_ROADMAP.md": "66347004b3e75546850a159857d039c14a5541fc13f91036d33edb79a4ff75c1",
    "docs/ash-cosmology/branch-centered-roadmap/v0.2/human-readable/11_BRANCH_CORRECTION_LOCK.md": "748760b910c326e65ad8585a34dcf3168fffdd289bc91b80703ec6c5304a1a77",
    "docs/ash-cosmology/branch-centered-roadmap/v0.2/source-evidence/ASH-Model-v1.1.0-computational-certificate.json": "e37e4fce9c3e66e20bc70ca864489b37052ef1fd28ad66d9bf02fcf668c0c496",
    "docs/ash-cosmology/branch-centered-roadmap/v0.2/source-evidence/ASH_Model_Audit_Validation_and_Remediation.md": "62ad9e0730df8bda97ae2dbebdf30e2cd77bc103230da270fe8e06b21bb92cfa",
    "docs/ash-cosmology/branch-centered-roadmap/v0.2/source-evidence/ASH_Model_Final_Verification.json": "f0cc3ce7b9110e5a51f90993535e90289a519b70743cd55a4ed23f5003c44342",
    "docs/ash-cosmology/branch-centered-roadmap/v0.2/source-evidence/ASH_Model_Full_Repository_Audit.md": "8cce05a4304ff50312291cec5f836a296dcbf9de55872d4a15487c2d788829bd",
    "docs/ash-cosmology/branch-centered-roadmap/v0.2/source-evidence/ASH_Model_Original_Audit_Reproduction.json": "8d13c8b438bd0f7fb8472346caf98ab94ba33b59dce72d3cd9025ab4d36833fe",
    "docs/ash-cosmology/branch-centered-roadmap/v0.2/source-evidence/ASH_Model_Verifier_Negative_Tests.json": "8bfb9736eb70c1b82717bfdf333097de18ab2c96ea933bbd0f6162e0d43b8847",
    "docs/ash-cosmology/branch-centered-roadmap/v0.2/source-evidence/README.md": "27e00e2f8bc1af8b4249cfc547332de5724884f27ff967c139ff6a5ea5db2c99",
    "docs/ash-physics-validation/IMPLEMENTATION_INSTRUCTIONS.md": "de06725adb28a0020eae3c3164008d57f2ffa9227777603b5ad1f24ec6cbac31",
    "docs/ash-physics-validation/PACKAGE_MANIFEST.json": "d3ed360f74ee7537b11783e6113045ff19239ee4c8ef5c82405ce6367a061aa9",
    "docs/ash-physics-validation/PACKAGE_QA.json": "0d959a19221b586333d80e3b7fd072a3eaa6827c1b288c163f53175e2ee9ef37",
    "docs/ash-physics-validation/README.md": "6a3c9fe39f3ce5c210e7c6fac73020a232841e7e555e9e62b97c52c389657c60",
    "docs/ash-physics-validation/configs/prediction_ledger.schema.json": "946103ea52d78095680d8b29e88c6b6e38471e2bbcaa26184181076b276c02b2",
    "docs/ash-physics-validation/configs/preregistration.schema.json": "99519298a65bb1ba8b2c18107f9e38d414bf50105e27d4b58af39abe5b8d8ed6",
    "docs/ash-physics-validation/configs/proof_certificate.schema.json": "9f5a26de5d7fdc16516d423c13b9c0e5c8243876d47d689c9183f590c165866f",
    "docs/ash-physics-validation/configs/proof_certificate_actual_shape_notes.md": "7964161554ea03347b3966647ff6a4b6dd0f841dd2e7dea61a928199c626e043",
    "docs/ash-physics-validation/configs/science_manifest.schema.json": "f78f41cd9d51f4b8936fa4ef021559dcb7c6338235eb2503324ca06252d2c047",
    "docs/ash-physics-validation/configs/task_manifest.schema.json": "1fda2013cc56094c70ef2b26ed716e9e95621384ad96a8f0b8aaf475c498f9b4",
    "docs/ash-physics-validation/configs/validation_status.schema.json": "5f1194aa46541af4a8e1114df4cd8a1800e2020d15d4fe17ed09a775f5c4d915",
    "docs/ash-physics-validation/docs/01_mathematical_proof_program.md": "6c5940318fde72e1b7a108d8cfeac2d568755cf3e59f507ef95027e2450c8661",
    "docs/ash-physics-validation/docs/02_physical_bridge_specification.md": "cd28da118ce071d419893adbaf965572fec525938c57d9a03a23f4eb7485856a",
    "docs/ash-physics-validation/docs/03_empirical_validation_program.md": "d94d0665685da9771a7355db290ce87f38fdaa4b452fd9c20f9649bd78edfa03",
    "docs/ash-physics-validation/docs/04_falsification_and_acceptance_gates.md": "77e17a8c5d9788d58f083176c1aa299c24578b671b776f621503ef2f0924617d",
    "docs/ash-physics-validation/docs/05_repository_integration_plan.md": "0f48dcacedcaf88f4e7f1f269e1a359d6d4d32a4c31247606e3404edecabb07c",
    "docs/ash-physics-validation/docs/06_language_and_claim_policy.md": "051eea5ed50f9ade81ee3b63eea96b53fd8637953b65db16e135b85208b7681e",
    "docs/ash-physics-validation/reference/ASH-Model-v1.1.0-computational-certificate.json": "e37e4fce9c3e66e20bc70ca864489b37052ef1fd28ad66d9bf02fcf668c0c496",
    "docs/ash-physics-validation/reference/ASH_Model_Audit_Validation_and_Remediation.md": "d52e830787255e6180cb04639199612c06bc7708933c306810f9ddfcff4167ad",
    "docs/ash-physics-validation/reference/ASH_Model_Final_Verification.json": "f0cc3ce7b9110e5a51f90993535e90289a519b70743cd55a4ed23f5003c44342",
    "docs/ash-physics-validation/reference/ASH_Model_Original_Audit_Reproduction.json": "8d13c8b438bd0f7fb8472346caf98ab94ba33b59dce72d3cd9025ab4d36833fe",
    "docs/ash-physics-validation/reference/ASH_Model_Verifier_Negative_Tests.json": "8bfb9736eb70c1b82717bfdf333097de18ab2c96ea933bbd0f6162e0d43b8847",
    "docs/ash-physics-validation/scripts/check_claim_language.py": "170dd05acfaa94c7c1b110c08cf257c8f03b1f41cef2e6eae398219cd90767c2",
    "docs/ash-physics-validation/scripts/check_sensitive_language.py": "9681a7ec3cca063ad1dcf1278b846ed62427645ede1b084b26def9447d023a00",
    "docs/ash-physics-validation/scripts/run_repository_gate.py": "16f37af7e713816e1d6091f1aee6cbd58dbfea0eb5ab176ad7b7766a0555dc5a",
    "docs/ash-physics-validation/sector-mixing-resolution-pass-002.md": "062059f8eb7ca3e8af1842f0fbbd602104d61a9be7622c7c34c8b219f865fd8f",
    "docs/ash-physics-validation/tasks/empirical_backlog.json": "c7fd48801e84953d845ac4b2f8d072f5b06d3e870c20cdc00e15f505437f24af",
    "docs/ash-physics-validation/tasks/proof_backlog.json": "3ce4132a5c5bdee7871f0a50a94603ec1716b203c75e504c6925f97ad0e06db2",
    "docs/ash-physics-validation/tasks/science_manifest.json": "682d97c2d5e918d49699883b0b6d5a5be2d4c13e52b2b15a660ca303a2fac8fd",
    "docs/ash-physics-validation/tasks/task_manifest.json": "75102597ccae592fd0abde233b4cf1a8310e9f4de293f14686e1c5118e1a155a",
    "docs/ash-physics-validation/templates/preregistration.md": "34bd9912356c4d9a066306524ee1113e95b8785cfe19fcd06a799f62edf976d8",
    "docs/ash-physics-validation/templates/theorem_catalog.md": "721911b1ff676359a9587e8c78684771119630a2eb612365a7a371bbdde23d0c",
    "docs/ash-physics-validation/templates/validation_status.json": "6b7d036ea97b154c524e3f170ff20b0a1e3d7a79ac3694ce5952bed5ef58cc95",
    "docs/audit-resolution.md": "2fea49077e41d3e83bf0852ed6001d2d1326fd60f36050cab24f89eea32169d0",
    "docs/canonical-computational-specification.md": "4ab825d8722e00b035e75b653a23dc176e2a96b51414241d0199946700789ddd",
    "docs/consistency-validation-report.md": "693ff368d5962591adf87cbab231867d2fa2d00273692f91f970eb5d37cd73eb",
    "docs/data-accuracy-audit.md": "75d920e7b03ca0b43f0f5dc5bb27ffabe585781513281b9e30cacfc66c7786c3",
    "docs/falsification-and-controls.md": "8c21ebde99b63d10d57117a615a639927df35251472b15d731de402fa1e229fe",
    "docs/final-live-repository-audit.md": "32c617978bcd68e212a46f30b0439b7e2a6ee8fe7e5ef19e56c3cc3392935597",
    "docs/governance/discussion_moderation_policy.md": "9c56afb1fa37b35c9ea1e7ec11929b1b55fb0431305ad0415b64d8c7a5e5537c",
    "docs/governance/github_automation_agents.md": "d8888d256267229c3d9fcef26cd2bf3a038207569f9143410c16585cbd544441",
    "docs/mathematical-accuracy-review.md": "03f0b720fe288b5246ba6411182e8ac84093a95e83d8c2a6fc6aa6ddfa412679",
    "docs/mathematical-proof.md": "298278413efaba66f1730b5bd496e281188a8e7d2de0b7a3960fe4571e4591bb",
    "docs/mirmir-integration.md": "3293da531348521e97341a181be56ee8b8357ecb723a25ac8b395a1b913bfaca",
    "docs/python-code-validation.md": "ec6a5f9dc9e6637e9e65f0a27d14f807846b35a3647be530bdb59ba85dbd9e97",
    "docs/remediation/final-repository-remediation.md": "4904ba7b0864668c1c6d1f437502a4231cd9e779ba7c2d174e8a5cecd75496c0",
    "docs/repository-review.md": "7ba3bf95529a084fde28b982403b89b96904b0e4d4c5415865b240fd1ae0a828",
    "docs/wiki-publication.md": "cca906c970d70f6515039d7b810462316df281e1d7dacb77d44d85563e3af5ab",
    "figures/ash-physics-sector-mixing/README.md": "b78daa966591e0dcd99563241fd542d548871f5a7d5bf1d7db9ab14d82cbc429",
    "latex/main.tex": "5a232384db3674574114b947ac1dfe447cb9abb3aebb24f80f89530e931502fa",
    "phenomenology/README.md": "981970197971fc45912f36ebf67251110aef844c7a4309625285e5a6fd8edaec",
    "phenomenology/ash_background_spec.md": "4211ddfb039f15c2326885a9b92bd731a218571fc69fcb7f54f9538aea5dc7f1",
    "phenomenology/ash_perturbations_spec.md": "9ad6c991ca405a6f8419a316c9efc11f52d393e454bd3aaa2cb28e93e7e81ee4",
    "phenomenology/observables_spec.md": "50a261daa13afdd7a7387a6fcd2457710a8af95635292bcb486fc4cfe0111c8a",
    "phenomenology/primordial_spectrum_spec.md": "eb636ade08319c8527ee40102a1b569674bf88ee18fe979ed2b1aef8836ee654",
    "predictions/falsification-criteria.md": "182012217051bdce79a96d37f740739a0c4be4475a6b4cba47b095554512c010",
    "predictions/prediction-ledger.json": "ced86e9d9bf2a3a4613317fbdb83546b5315b4c073f81086af46ba7040b18393",
    "pyproject.toml": "444e6da8b4fee8a993a3e7fb270b80d624943c9d26a9a95ac875c4d7fe5defc2",
    "scripts/github/check_contributor_identities.py": "84a4ccb373b02796c816246e95dc3b4c7a482efdf168f4b6ba2d6bb4e627fc1c",
    "scripts/github/discussion_agent.py": "8a4cda43bb2df75c106eb86622ccb54cdb6c8a83d0c9959b309d951b28c33361",
    "scripts/github/discussion_moderation_agent.py": "02430dd7c1a761aa31cc20b84627d2151d80a09071b94c5fe43752d13c0a7c2a",
    "scripts/github/discussion_topic_agent.py": "1a5bad3b569dc065589b3cf1553be253fdf628d28741d07c98bf9214b5059c94",
    "simulation.py": "3f3cdb342062deb2c19d10d561abed6918556ea40516b53d0e424b7bf11054f9",
    "src/ash_model/__init__.py": "eeafa8deff5346e2d2ba3c494c02d43d11f06367461a43976400f62695308bca",
    "src/ash_model/adinkra.py": "13f360b11b95033940ead7fd507664e3ce81b14c53921bc68d7223ff223f86c0",
    "src/ash_model/bits.py": "cdcc9027da11b4dcae5d6bd53dda404d021dee10b01bbf0f86dd9be1c9d481cb",
    "src/ash_model/branching.py": "7c6378e1a3f03e7d277bca04651eaf3d24b5e4cb15799c106c99a76d2f2c3ef3",
    "src/ash_model/code.py": "272a91ad1af3e51d6b9fe2545212448cefb404e0818d55c5623441ae636ba992",
    "src/ash_model/cosmology.py": "3839c1ddabffc7aa364f595eef78c86a62f13e89793917f3be7a1f2c2a39ffdb",
    "src/ash_model/empirical.py": "320b1013c6770c153d56fe9235ac8299551003937151c5326790f005b90ce41f",
    "src/ash_model/features.py": "47f31bde543768caee3e325edffb60770c2a93428a32479dfbfeeccfda77de30",
    "src/ash_model/hypercube.py": "b03528c7c7e860f7d7ddc5cb8f5d56115ba563499d9b55d2e269afc67c1feef8",
    "src/ash_model/physics.py": "8bcefa17facccf9d05b7d40f9ddcc4c912a3a2cf9c6888ec3995d9dcabe71ce7",
    "src/ash_model/pipeline.py": "8bd106051a922721836df78584ce478c3ecda2072264970b477a104a0fbecc77",
    "src/ash_model/prediction_ledger.py": "2e5a582da290c44c098b1844952650cdde798fa4814b39d235f33b2c9a2bdde0",
    "src/ash_model/projection.py": "4ef9c24d8143e669c1d88a086d25aa2e1f6f199e259ddadaaeb9c5c1101fc1f1",
    "src/ash_model/reconstruction.py": "89dc2de96f75d0ccedc1be7d48c4f558071270650806daaf58ae4c3ed313fc1f",
    "src/ash_model/simulation.py": "5c36fec87dd170cb57bcd898f4ac7ad5fb94b90c5c2aa21670269bf8a3a0915f",
    "src/derive-9-properties.py": "161d6961d49754fafac653c4833546825be887e39153bc0b21fda93dfa1ad2a5",
    "src/simulate.py": "54cdfaa1f1f26dc21c594c4c4f60a0021cd2ea618eab6354a4ad8e6d859e6877",
    "tests/test_bits_hypercube.py": "9b6ef1be9223b77737f284dd9bbc3b94fbdca8c0beeda3602b720c1a316bbd34",
    "tests/test_branching_reconstruction_pipeline.py": "42e3ccd646576b8ed58e63175d69222473287112ab3e1fcf34de87ea50112a79",
    "tests/test_code.py": "828c64a45a500444c31359b6f06c2ffaec8296268670e201ab29259bcb073110",
    "tests/test_config_conformance.py": "5b9ea1e97bdc9095c95c455e778212451649fb331776f9047bb3379f7f96e244",
    "tests/test_contributor_identity_check.py": "1d72fd96870dfe23ead93a2871d9bc043728450560676af2698da97b8b6a0546",
    "tests/test_cosmology.py": "2e7aaa7bb005217f34e7267b5573273fd5177fd3ffb2de29900b3ee3b834d83f",
    "tests/test_empirical_bridge.py": "70c122a8d4df6763e50caa986949dc0b8354c698c28d846cb7de8cd42d9f03ac",
    "tests/test_features.py": "684952b4a4a6583cab344a9aab25de78e6a6a7bab0735faf1f4d7076186919ab",
    "tests/test_final_repository_remediation.py": "55a27227dd231c208b368305b670bb8e420ebc8a6f9077956eea252b3d5f0cac",
    "tests/test_physics.py": "326df9bb2444304f35c9c201efbe88e8924012698621be1ff799071deba263b8",
    "tests/test_prediction_ledger.py": "99a68a6d997a6f068a59c7c611c2fa63db0e9fc34ce2caeb232ecc0a57b018a3",
    "tests/test_projection_adinkra.py": "690225ebfa30dcd12a80fc4b48005cc1619bcf66e498579d02787015462cfee2",
    "tests/test_repository_claims.py": "a634a52f2bccb766e2a07f6772de77c9dbccb83b4d8ec33df91aa2e5859893c6",
    "tests/test_repository_integrity.py": "793a957c7552e0713097154da2b2ec40d367f73839e1dad2f62367b56c1fdad8",
    "tests/test_sector_mixing.py": "1321dc81f7d5a4a30ba523a85c220ef5c247efee9e0c646e508ebac0d217dc07",
    "tests/test_simulation.py": "d18efb724b9d4e6e658c460cd92a287c9d7f3500a6e902b84dd01d479b4e1eca",
    "theory/causal-structure.md": "c80b59885e9251dffbb3337e129de3dfc63482a6f9d03aee5334dc69f359d137",
    "theory/coarse-graining-and-bridge-map.md": "4fe127fcdc36487305ca520624ec9e249c6ed8024eb79210c98f3c7feb487296",
    "theory/continuum-limit.md": "40f645992328e96cfff0f597aebd07da42d24151b4d70dd9e2465f2c94cb1e37",
    "theory/cosmological-background.md": "e0d5bd699a45097b0b3aa1c28294a96b60dcf1748d8e5a9d5c6a34868d95c868",
    "theory/linear-perturbations.md": "ee681b628a4efc0be20ab72e054bb7c7b952e5a3e1eae9c265d796e95b016583",
    "theory/microscopic-state-and-dynamics.md": "a543635fa29116e2c4e6c3f7627e13ad838b7b09885b749871ee921490e06543",
    "theory/physical-postulates.md": "78d12f2a46c266a3140b15d72893a80dbd9bdc6034d89bf4cc821cdd4f5b7aba",
    "tools/__init__.py": "a61d112f13d4188ec891315ea0f254d0131bd9ccd1847229dbb3d2469e0bb7de",
    "tools/audit_live_repository_readiness.py": "dd62bcdcffc0efaa67dbfba97d915653bbc3fbdd493fa964e16be0a27e5383bd",
    "tools/audit_physics_readiness.py": "70a4a6c03edb30cdc72740bd7039358defa97e811f3a4b8b91b2b4c320df3ea0",
    "tools/audit_simulation_data.py": "0b2be60bff931968223e99d6b8b830cc9667e016b56ed6521e05aff413bac090",
    "tools/build_manuscript.py": "140ea976847ca516a5321d5c34c46da9fd4a69bb9b2e51754dfcece978be457b",
    "tools/check_generated_outputs.py": "afa7994864e80c1a4626ddc8103c8c237ee741f1a0fde76c73b14e5b53270906",
    "tools/final_repository_audit.py": "ba12ee95ed31886daa627e15e3840fa011043a270adee26af495eaf20567e417",
    "tools/generate_artifacts.py": "92c8c6f8c2e2bbdc12a6b4bd3da50ac1f85e5cd8f76f89e14a3415d4818142bf",
    "tools/reproduce_sector_mixing.py": "05a8d4a014c7990b54ba192bc139ad120663c580d2096412da73dbfc7206042c",
    "tools/run_proof_suite.py": "e8b5824028fad85f7147bc259c83853c9277c573c608efe3b1dfde536c77f71c",
    "tools/validate_json_assets.py": "8ee57ce266de3df05effdeaff25e0138c8c21463ae4749f5108e7c0683a2f96f",
    "tools/verify_repository.py": "f05ff69a07dd01f211dc6a9a9348a696ae6caee8c3067ab354a1f35dbc5cd126",
    "validation/lcdm-limit/README.md": "b03ac3bba6122bf3e4e505c3f1188e8ddf1203ed27fae0a24f16d88b36e0b555",
    "validation/matched-ablations/README.md": "004b2df17503b5276b0b63e00469e439bb52983d440ee2f286d5dc6f2372a5b9",
    "validation/numerical-convergence/README.md": "c04c5bbf76f8efc0bf1ae7a699b8fceed01be7a421e225c59fd61e81e9abe7ac",
    "validation/preregistration.md": "74d5875c196627430cc959cbbcacfbdfec13c011e1b5f82b1c03b38782ca0fd6",
    "validation/status.json": "21330b6683b4aef80d2131b1075f017e423ae0232cbf9ec6e645c0fb3f12eb4f",
    "validation/synthetic-recovery/README.md": "f74a411ab65daef967315632f19b362b81f96602ff4b4e1451047e3e2b31063f",
    "wiki/ASH-Cosmology-Branch-Centered-Roadmap.md": "11cf20e8c99e1545fd46715b882d5b7aecc894ac905db42f852d6115f96172b4",
    "wiki/ASH-Cosmology-Branch-Correction-Lock.md": "198d2b5f9b0fcd902fdf153d7aececaa233821334e2dffb58a2006ef5473a0a7",
    "wiki/Axioms-of-Existence.md": "b16acfb9547d42490cb2d3817a01afa6b0e892080b1c8612892fe03b857aeda1",
    "wiki/Codebase-Overview.md": "e43a2488e437363a0ec99933eb81cff9ae8eebbbe62b9a4276408fb01aa4ad7a",
    "wiki/Consistency-Checklist.md": "7980ef7e546f8e28d71c886059390d7de191e52c67eaeb76146b7e155dbc7ad0",
    "wiki/Contributing-Guidelines.md": "932ab0b5159662d1e8c4058865c77b333f43334f5f2efc6f2442ddf83030d822",
    "wiki/Evidence-and-Artifacts.md": "0bdd6a6a9930e1ea359c621f94fef28dc9babb47099cdfb97ef638675a2055ac",
    "wiki/Examples-and-Tutorials.md": "315bc4ebbf4117a5223248a50236f60ec4e47466c4f8e35b43191b79453f5079",
    "wiki/Finite-Observer-Physics.md": "b6dbb9136dfc5e79a328f42f45403e4f3c4403b50d93d94b7d2a0722775192e7",
    "wiki/Getting-Started.md": "d928221d4eb77a012bd95a65356bb49bf13d3bf29f70a9bea26fb441255a17b3",
    "wiki/Governance-and-Discussions.md": "e335be1901a431458c6e26936f4314654103ba46937800a1fe1e2a2953ef7e5c",
    "wiki/Home.md": "76404f676ccf82d672a1ae1c0d345fff250501a9cbcfb6055608050ae6db0665",
    "wiki/Hypercube-and-Adinkra-Visual-Guide.md": "5e1984fdf6344f3e5fe7908bb2a2966ac09a41e94178f3386f8792db999309f6",
    "wiki/Introduction-to-ASH-Model.md": "6f434a744a7247f7974953de4aeb2b94a1a3c7a1156c77118d00bd1988698c10",
    "wiki/License-and-Use.md": "10c5d8e8ad58b066175ec3a7caa7c609db558e4a03977e8851b4859efce25e31",
    "wiki/Mathematical-Framework.md": "611e25035d6fdc3e811442d01010d83d2ed5b1c64582f6f73373d2ed8bdf080d",
    "wiki/References-and-Further-Reading.md": "4a6ef9d73541b874f6a7daf6d97c352133aefdea1fc5aeeab01544645a24b1e2",
    "wiki/Repository-Structure.md": "411d1a4dafe21e428b2f5071ea3bb4ecc975f0eb7b1879c32aedd3a432ceddae",
    "wiki/Research-Paper-Guide.md": "5a1e2e6655cd01e2a20bbec223dd0c3ca40dc7a2954b0d8b3658d699b005a902",
    "wiki/Science-Roadmap.md": "403def76611e5768985e84dd2883bc9e1c283d433af9f4de1ec38fbbf65526b6",
    "wiki/Simulation-Guide.md": "d79f88214c18c58fd9e86d97478c2ac9d84b237f1614f105838ae513ea3a3586",
    "wiki/Theoretical-Applications.md": "071f2b607ea447c818f649d60e4bfd3f435d888384de72742c1d59222a4a1e7a",
    "wiki/Validation-and-Data-Audit.md": "2836ef82adaf588f6520c5c3350577d88c9772cb86293b78c10e823d4502ec97",
    "wiki/Visual-Model-Atlas.md": "a8dcd12367b88a5fccb2a66ea9c34fc9bbb3a2301b516f07a3d2ac9b59b6d5d9",
    "wiki/_Footer.md": "e02c73ef3e2fa716b4570da70d0b83a87a66dddd065fbf18b92586fddc8ad507",
    "wiki/_Sidebar.md": "b1f916d8bc9f09a59d1a7df66e418baf40a4bbc434d3ca019261d6ca5bfc480a"
  }
}
