{
  "schema": "ash.skir.controls.v1",
  "quick": true,
  "seed": 20260613,
  "interpretation": "Controls compare ASH codeword transforms with no-codeword and random-codeword baselines. They support conservative language about noisy hypercube mixing and do not by themselves prove runtime error correction.",
  "runs": [
    {
      "name": "ash_codewords_noise",
      "agents": 500,
      "ticks": 200,
      "noise_prob": 0.01,
      "start": "random",
      "hamming_weight_counts": [
        2,
        10,
        38,
        79,
        112,
        119,
        93,
        39,
        8,
        0
      ],
      "tvd_to_binomial": 0.03978125
    },
    {
      "name": "no_codewords_noise",
      "agents": 500,
      "ticks": 200,
      "noise_prob": 0.01,
      "start": "random",
      "hamming_weight_counts": [
        0,
        6,
        33,
        91,
        129,
        113,
        77,
        45,
        6,
        0
      ],
      "tvd_to_binomial": 0.04953125
    },
    {
      "name": "random_codewords_noise",
      "agents": 500,
      "ticks": 200,
      "noise_prob": 0.01,
      "start": "random",
      "hamming_weight_counts": [
        1,
        13,
        35,
        96,
        113,
        118,
        87,
        28,
        9,
        0
      ],
      "tvd_to_binomial": 0.046765625
    },
    {
      "name": "all_zero_ash_no_noise",
      "agents": 500,
      "ticks": 200,
      "noise_prob": 0.0,
      "start": "zero",
      "hamming_weight_counts": [
        0,
        0,
        0,
        0,
        500,
        0,
        0,
        0,
        0,
        0
      ],
      "tvd_to_binomial": 0.75390625
    },
    {
      "name": "all_zero_ash_noise",
      "agents": 500,
      "ticks": 200,
      "noise_prob": 0.01,
      "start": "zero",
      "hamming_weight_counts": [
        1,
        6,
        37,
        89,
        128,
        131,
        68,
        35,
        4,
        1
      ],
      "tvd_to_binomial": 0.043531249999999994
    }
  ]
}